schedule_jobs/__init__.py
schedule_jobs/app.py
schedule_jobs/test.py
schedule_jobs/core/__init__.py
schedule_jobs/core/base_job.py
schedule_jobs/core/helper.py
schedule_jobs/jobs/__init__.py
schedule_jobs/jobs/test_job.py
schedule_jobs-0.0.4.dist-info/DESCRIPTION.rst
schedule_jobs-0.0.4.dist-info/METADATA
schedule_jobs-0.0.4.dist-info/RECORD
schedule_jobs-0.0.4.dist-info/WHEEL
schedule_jobs-0.0.4.dist-info/metadata.json
schedule_jobs-0.0.4.dist-info/top_level.txt
