Metadata-Version: 2.0
Name: schedule-jobs
Version: 0.0.4
Summary: A Schedule Jobs Library
Home-page: https://github.com/Tsotsi/schedule_jobs
Author: Tsotsi
Author-email: tsotsi@tsotsi.cn
License: UNKNOWN
Platform: UNKNOWN
Classifier: Programming Language :: Python :: 3.6
Classifier: Programming Language :: Python :: 3.7
Classifier: License :: OSI Approved :: MIT License
Classifier: Operating System :: MacOS
Classifier: Operating System :: POSIX :: BSD
Classifier: Operating System :: POSIX :: Linux
Requires-Python: ~=3.6
Requires-Dist: schedule (<1,>=0.5.0)
Requires-Dist: six (<2,>=1.11.0)
